<?xml version="1.0" encoding="utf-8"?>
<ModReplacement>
  <Author>Sea</Author>
  <ModId>Xenofell.LadiesCanFlirtToo</ModId>
  <ModName>Ladies Can Flirt Too!</ModName>
  <ReplacementAuthor>Mlie</ReplacementAuthor>
  <ReplacementModId>Mlie.LadiesCanFlirtToo</ReplacementModId>
  <ReplacementName>Ladies Can Flirt Too! (Continued)</ReplacementName>
  <ReplacementSteamId>3559816908</ReplacementSteamId>
  <SteamId>2725963995</SteamId>
  <Versions>1.3,1.4</Versions>
  <ReplacementVersions>1.3,1.4,1.5,1.6</ReplacementVersions>
</ModReplacement>
