<?xml version="1.0" encoding="utf-8"?>
<ModReplacement>
  <Author>76561198355960890</Author>
  <ModId>stormtrooper.rebelpsycasts</ModId>
  <ModName>Rebel Psycasts</ModName>
  <ReplacementAuthor>Zaljerem</ReplacementAuthor>
  <ReplacementModId>zal.rebelpsycasts</ReplacementModId>
  <ReplacementName>Rebel Psycasts (Continued)</ReplacementName>
  <ReplacementSteamId>3599392042</ReplacementSteamId>
  <SteamId>2885420111</SteamId>
  <Versions>1.4</Versions>
  <ReplacementVersions>1.5,1.6</ReplacementVersions>
</ModReplacement>
