<?xml version="1.0" encoding="utf-8"?>
<ModReplacement>
  <Author>emitbreaker</Author>
  <ModId>emitbreaker.MIM.WH40k.NC.SA</ModId>
  <ModName>MIM - WH40k Sautekh</ModName>
  <ReplacementAuthor>emitbreaker</ReplacementAuthor>
  <ReplacementModId>emitbreaker.MIM.WH40k.NC.SA</ReplacementModId>
  <ReplacementName>MIM Warhammer 40k Sautekh</ReplacementName>
  <ReplacementSteamId>3517419656</ReplacementSteamId>
  <SteamId>3092955929</SteamId>
  <Versions>1.4,1.5</Versions>
  <ReplacementVersions>1.6</ReplacementVersions>
</ModReplacement>
