<?xml version="1.0" encoding="utf-8"?>
<ModReplacement>
  <Author>viva</Author>
  <ModId>durex.ghoulimplantsforhuman</ModId>
  <ModName>Ghoul Implants for Human</ModName>
  <ReplacementAuthor>Durex, Port by Starfield</ReplacementAuthor>
  <ReplacementModId>durex.ghoulimplantsforhuman</ReplacementModId>
  <ReplacementName>Ghoul Implants for Human [1.6]</ReplacementName>
  <ReplacementSteamId>3539656755</ReplacementSteamId>
  <SteamId>3254236631</SteamId>
  <Versions>1.5</Versions>
  <ReplacementVersions>1.5,1.6</ReplacementVersions>
</ModReplacement>
